server_system_monitor/__init__.py
server_system_monitor/connection_monitor.py
server_system_monitor/monitor.py
server_system_monitor/server_client_monitor.py
server_system_monitor-0.1.1.dist-info/licenses/LICENSE
server_system_monitor-0.1.1.dist-info/METADATA
server_system_monitor-0.1.1.dist-info/WHEEL
server_system_monitor-0.1.1.dist-info/top_level.txt
server_system_monitor-0.1.1.dist-info/RECORD
