Metadata-Version: 2.4
Name: server_system_monitor
Version: 0.1.1
Summary: A server system monitor for linux to linux
Author-email: FaboBorgesLima <fabo.borges.lima@gmail.com>
Maintainer-email: FaboBorgesLima <fabo.borges.lima@gmail.com>
License: The MIT License (MIT)
Keywords: monitor,system,server,remote
Classifier: Intended Audience :: Developers
Classifier: Operating System :: POSIX :: Linux
Classifier: Programming Language :: Python :: 3
License-File: LICENSE
Requires-Dist: paramiko
Provides-Extra: dev
Requires-Dist: check-manifest; extra == "dev"
Provides-Extra: test
Requires-Dist: coverage; extra == "test"
Dynamic: license-file
